colorful_logging/__init__.py
colorful_logging/colorful_logging.py
colorful_logging-0.9.dist-info/METADATA
colorful_logging-0.9.dist-info/WHEEL
colorful_logging-0.9.dist-info/top_level.txt
colorful_logging-0.9.dist-info/RECORD
