Metadata-Version: 2.1
Name: colorful_logging
Version: 0.9
Summary: A library to print colorful
Home-page: https://github.com/zamoosh/colorful_logging
Author: zamoosh
Author-email: moyi.pary@gmail.com
License: MIT
Keywords: colorful logging,color printing,color output
Platform: UNKNOWN
Classifier: Development Status :: 4 - Beta
Classifier: Intended Audience :: Developers
Classifier: License :: OSI Approved :: MIT License
Classifier: Programming Language :: Python :: 3
Classifier: Programming Language :: Python :: 3.6
Classifier: Programming Language :: Python :: 3.7
Classifier: Programming Language :: Python :: 3.8
Classifier: Programming Language :: Python :: 3.9
Classifier: Topic :: Software Development :: Libraries :: Python Modules
